fijibin/__init__.py
fijibin/macro.py
fijibin/VERSION
fijibin-0.3.0.dist-info/DESCRIPTION.rst
fijibin-0.3.0.dist-info/METADATA
fijibin-0.3.0.dist-info/metadata.json
fijibin-0.3.0.dist-info/RECORD
fijibin-0.3.0.dist-info/top_level.txt
fijibin-0.3.0.dist-info/WHEEL
