Metadata-Version: 2.0
Name: fijibin
Version: 0.3.0
Summary: Latest Life-Line version of Fiji for easy inclusion in python projects.
Home-page: https://github.com/arve0/fijibin
Author: Arve Seljebu
Author-email: arve.seljebu@gmail.com
License: MIT
Platform: UNKNOWN
Requires-Dist: pydebug
